django_core/__init__.py
django_core/admin/__init__.py
django_core/apps.py
django_core/exceptions/__init__.py
django_core/exceptions/core.py
django_core/management/__init__.py
django_core/management/commands/__init__.py
django_core/management/commands/seed.py
django_core/management/core.py
django_core/migrations/0001_initial.py
django_core/migrations/__init__.py
django_core/mixins/__init__.py
django_core/mixins/base.py
django_core/models/__init__.py
django_core/models/base.py
django_core/models/user.py
django_core/paginations/__init__.py
django_core/paginations/default.py
django_core/permissions/__init__.py
django_core/permissions/role.py
django_core/serializers/__init__.py
django_core/serializers/translated.py
django_core/tasks/__init__.py
django_core/tasks/sms.py
django_core/templatetags/__init__.py
django_core/views/__init__.py
django_core/views/dashboard.py
jst_django_core-1.2.2.dist-info/LICENSE
jst_django_core-1.2.2.dist-info/METADATA
jst_django_core-1.2.2.dist-info/WHEEL
jst_django_core-1.2.2.dist-info/RECORD
